api_schema_diff-1.0.4.dist-info/licenses/LICENSE
schema_diff/__init__.py
schema_diff/cli.py
schema_diff/diff.py
schema_diff/loader.py
schema_diff/models.py
schema_diff/rules.py
schema_diff/openapi/__init__.py
schema_diff/openapi/diff.py
schema_diff/openapi/json_schema_diff.py
schema_diff/openapi/normalizer.py
schema_diff/openapi/resolver.py
api_schema_diff-1.0.4.dist-info/METADATA
api_schema_diff-1.0.4.dist-info/WHEEL
api_schema_diff-1.0.4.dist-info/entry_points.txt
api_schema_diff-1.0.4.dist-info/top_level.txt
api_schema_diff-1.0.4.dist-info/RECORD
