Metadata-Version: 2.4
Name: api-schema-diff
Version: 1.0.4
Summary: Detect breaking changes between API schemas (OpenAPI / JSON Schema)
Author: Teodor Lazar
License: MIT
Project-URL: Homepage, https://github.com/teolzr/schema-diff
Project-URL: Repository, https://github.com/teolzr/schema-diff
Project-URL: Issues, https://github.com/teolzr/schema-diff/issues
Keywords: openapi,json-schema,api,diff,breaking-changes,ci-cd,schema-validation
Classifier: Development Status :: 4 - Beta
Classifier: Intended Audience :: Developers
Classifier: License :: OSI Approved :: MIT License
Classifier: Programming Language :: Python :: 3
Classifier: Programming Language :: Python :: 3.10
Classifier: Programming Language :: Python :: 3.11
Classifier: Programming Language :: Python :: 3.12
Classifier: Programming Language :: Python :: 3.13
Classifier: Topic :: Software Development :: Quality Assurance
Classifier: Topic :: Software Development :: Testing
Classifier: Typing :: Typed
Requires-Python: >=3.10
License-File: LICENSE
Requires-Dist: typer>=0.12
Requires-Dist: rich>=13.7
Requires-Dist: pyyaml>=6.0
Provides-Extra: dev
Requires-Dist: pytest>=7.4; extra == "dev"
Requires-Dist: pytest-cov>=4.1; extra == "dev"
Requires-Dist: black>=23.12; extra == "dev"
Requires-Dist: ruff>=0.1; extra == "dev"
Requires-Dist: mypy>=1.7; extra == "dev"
Requires-Dist: build>=1.0; extra == "dev"
Requires-Dist: twine>=4.0; extra == "dev"
Requires-Dist: pre-commit>=4.0; extra == "dev"
Dynamic: license-file
